quest/__init__.py
quest/layers.py
quest/model.py
quest/model_utils.py
quest/trainer.py
quest/bench/__init__.py
quest/bench/bench_utils.py
quest/bench/generators.py
quest/bench/metric.py
quest_niche-0.1.4.dist-info/METADATA
quest_niche-0.1.4.dist-info/WHEEL
quest_niche-0.1.4.dist-info/top_level.txt
quest_niche-0.1.4.dist-info/RECORD
