Metadata-Version: 2.4
Name: quest-niche
Version: 0.1.4
Summary: Querying functional and structural niches on spatial transcriptomics data
Author-email: Mo Chen <mochenthu@gmail.com>
License: MIT
Classifier: Programming Language :: Python :: 3
Classifier: License :: OSI Approved :: MIT License
Classifier: Operating System :: OS Independent
Requires-Python: <4.0,>=3.8
Requires-Dist: numpy==1.23.4
Requires-Dist: pandas==2.2.1
Requires-Dist: scipy==1.9.1
Requires-Dist: scanpy==1.9.8
Requires-Dist: squidpy==1.4.1
Requires-Dist: networkx==3.2.1
Requires-Dist: scikit-learn==1.4.1.post1
Requires-Dist: umap-learn==0.5.5
Requires-Dist: anndata==0.10.6
Requires-Dist: leidenalg==0.10.2
Requires-Dist: igraph==0.11.4
Requires-Dist: graphcompass==0.2.2
Requires-Dist: torch>=2.2.1
Requires-Dist: torch-geometric>=2.5.2
